[
  {
    "type": "constructor",
    "inputs": [
      {
        "name": "accessController",
        "type": "address",
        "internalType": "address"
      },
      {
        "name": "ipRecordRegistry",
        "type": "address",
        "internalType": "address"
      },
      {
        "name": "ipAccountRegistry",
        "type": "address",
        "internalType": "address"
      }
    ],
    "stateMutability": "nonpayable"
  },
  {
    "type": "function",
    "name": "ACCESS_CONTROLLER",
    "inputs": [],
    "outputs": [
      {
        "name": "",
        "type": "address",
        "internalType": "contract IAccessController"
      }
    ],
    "stateMutability": "view"
  },
  {
    "type": "function",
    "name": "IP_ACCOUNT_REGISTRY",
    "inputs": [],
    "outputs": [
      {
        "name": "",
        "type": "address",
        "internalType": "contract IPAccountRegistry"
      }
    ],
    "stateMutability": "view"
  },
  {
    "type": "function",
    "name": "IP_RECORD_REGISTRY",
    "inputs": [],
    "outputs": [
      {
        "name": "",
        "type": "address",
        "internalType": "contract IPRecordRegistry"
      }
    ],
    "stateMutability": "view"
  },
  {
    "type": "function",
    "name": "_records",
    "inputs": [
      {
        "name": "",
        "type": "address",
        "internalType": "address"
      }
    ],
    "outputs": [
      {
        "name": "name",
        "type": "string",
        "internalType": "string"
      },
      {
        "name": "description",
        "type": "string",
        "internalType": "string"
      },
      {
        "name": "hash",
        "type": "bytes32",
        "internalType": "bytes32"
      },
      {
        "name": "registrationDate",
        "type": "uint64",
        "internalType": "uint64"
      },
      {
        "name": "registrant",
        "type": "address",
        "internalType": "address"
      },
      {
        "name": "uri",
        "type": "string",
        "internalType": "string"
      }
    ],
    "stateMutability": "view"
  },
  {
    "type": "function",
    "name": "accessController",
    "inputs": [],
    "outputs": [
      {
        "name": "",
        "type": "address",
        "internalType": "address"
      }
    ],
    "stateMutability": "view"
  },
  {
    "type": "function",
    "name": "description",
    "inputs": [
      {
        "name": "ipId",
        "type": "address",
        "internalType": "address"
      }
    ],
    "outputs": [
      {
        "name": "",
        "type": "string",
        "internalType": "string"
      }
    ],
    "stateMutability": "view"
  },
  {
    "type": "function",
    "name": "hash",
    "inputs": [
      {
        "name": "ipId",
        "type": "address",
        "internalType": "address"
      }
    ],
    "outputs": [
      {
        "name": "",
        "type": "bytes32",
        "internalType": "bytes32"
      }
    ],
    "stateMutability": "view"
  },
  {
    "type": "function",
    "name": "metadata",
    "inputs": [
      {
        "name": "ipId",
        "type": "address",
        "internalType": "address"
      }
    ],
    "outputs": [
      {
        "name": "",
        "type": "tuple",
        "internalType": "struct IP.Metadata",
        "components": [
          {
            "name": "owner",
            "type": "address",
            "internalType": "address"
          },
          {
            "name": "name",
            "type": "string",
            "internalType": "string"
          },
          {
            "name": "description",
            "type": "string",
            "internalType": "string"
          },
          {
            "name": "hash",
            "type": "bytes32",
            "internalType": "bytes32"
          },
          {
            "name": "registrationDate",
            "type": "uint64",
            "internalType": "uint64"
          },
          {
            "name": "registrant",
            "type": "address",
            "internalType": "address"
          },
          {
            "name": "uri",
            "type": "string",
            "internalType": "string"
          }
        ]
      }
    ],
    "stateMutability": "view"
  },
  {
    "type": "function",
    "name": "name",
    "inputs": [
      {
        "name": "ipId",
        "type": "address",
        "internalType": "address"
      }
    ],
    "outputs": [
      {
        "name": "",
        "type": "string",
        "internalType": "string"
      }
    ],
    "stateMutability": "view"
  },
  {
    "type": "function",
    "name": "owner",
    "inputs": [
      {
        "name": "ipId",
        "type": "address",
        "internalType": "address"
      }
    ],
    "outputs": [
      {
        "name": "",
        "type": "address",
        "internalType": "address"
      }
    ],
    "stateMutability": "view"
  },
  {
    "type": "function",
    "name": "registrant",
    "inputs": [
      {
        "name": "ipId",
        "type": "address",
        "internalType": "address"
      }
    ],
    "outputs": [
      {
        "name": "",
        "type": "address",
        "internalType": "address"
      }
    ],
    "stateMutability": "view"
  },
  {
    "type": "function",
    "name": "registrationDate",
    "inputs": [
      {
        "name": "ipId",
        "type": "address",
        "internalType": "address"
      }
    ],
    "outputs": [
      {
        "name": "",
        "type": "uint64",
        "internalType": "uint64"
      }
    ],
    "stateMutability": "view"
  },
  {
    "type": "function",
    "name": "setDescription",
    "inputs": [
      {
        "name": "ipId",
        "type": "address",
        "internalType": "address"
      },
      {
        "name": "newDescription",
        "type": "string",
        "internalType": "string"
      }
    ],
    "outputs": [],
    "stateMutability": "nonpayable"
  },
  {
    "type": "function",
    "name": "setHash",
    "inputs": [
      {
        "name": "ipId",
        "type": "address",
        "internalType": "address"
      },
      {
        "name": "newHash",
        "type": "bytes32",
        "internalType": "bytes32"
      }
    ],
    "outputs": [],
    "stateMutability": "nonpayable"
  },
  {
    "type": "function",
    "name": "setMetadata",
    "inputs": [
      {
        "name": "ipId",
        "type": "address",
        "internalType": "address"
      },
      {
        "name": "newMetadata",
        "type": "tuple",
        "internalType": "struct IP.MetadataRecord",
        "components": [
          {
            "name": "name",
            "type": "string",
            "internalType": "string"
          },
          {
            "name": "description",
            "type": "string",
            "internalType": "string"
          },
          {
            "name": "hash",
            "type": "bytes32",
            "internalType": "bytes32"
          },
          {
            "name": "registrationDate",
            "type": "uint64",
            "internalType": "uint64"
          },
          {
            "name": "registrant",
            "type": "address",
            "internalType": "address"
          },
          {
            "name": "uri",
            "type": "string",
            "internalType": "string"
          }
        ]
      }
    ],
    "outputs": [],
    "stateMutability": "nonpayable"
  },
  {
    "type": "function",
    "name": "setName",
    "inputs": [
      {
        "name": "ipId",
        "type": "address",
        "internalType": "address"
      },
      {
        "name": "newName",
        "type": "string",
        "internalType": "string"
      }
    ],
    "outputs": [],
    "stateMutability": "nonpayable"
  },
  {
    "type": "function",
    "name": "setURI",
    "inputs": [
      {
        "name": "ipId",
        "type": "address",
        "internalType": "address"
      },
      {
        "name": "newURI",
        "type": "string",
        "internalType": "string"
      }
    ],
    "outputs": [],
    "stateMutability": "nonpayable"
  },
  {
    "type": "function",
    "name": "supportsInterface",
    "inputs": [
      {
        "name": "id",
        "type": "bytes4",
        "internalType": "bytes4"
      }
    ],
    "outputs": [
      {
        "name": "",
        "type": "bool",
        "internalType": "bool"
      }
    ],
    "stateMutability": "view"
  },
  {
    "type": "function",
    "name": "uri",
    "inputs": [
      {
        "name": "ipId",
        "type": "address",
        "internalType": "address"
      }
    ],
    "outputs": [
      {
        "name": "",
        "type": "string",
        "internalType": "string"
      }
    ],
    "stateMutability": "view"
  },
  {
    "type": "error",
    "name": "IPResolver_Unauthorized",
    "inputs": []
  },
  {
    "type": "error",
    "name": "StringsInsufficientHexLength",
    "inputs": [
      {
        "name": "value",
        "type": "uint256",
        "internalType": "uint256"
      },
      {
        "name": "length",
        "type": "uint256",
        "internalType": "uint256"
      }
    ]
  }
]
